cometblue/__init__.py
cometblue/const.py
eurotronic_cometblue-1.1.1.dist-info/LICENSE
eurotronic_cometblue-1.1.1.dist-info/METADATA
eurotronic_cometblue-1.1.1.dist-info/WHEEL
eurotronic_cometblue-1.1.1.dist-info/top_level.txt
eurotronic_cometblue-1.1.1.dist-info/RECORD
