Metadata-Version: 2.1
Name: eurotronic-cometblue
Version: 1.1.1
Summary: Allows you to access Eurotronic GmbH BLE Comet Blue Radiator Controller
Home-page: https://github.com/zero-udo/eurotronic-cometblue
Author: Johannes Rottler
Author-email: johannes@rottler.me
License: MIT
Classifier: Programming Language :: Python :: 3.7
Classifier: Programming Language :: Python :: 3.8
Classifier: Programming Language :: Python :: 3.9
Classifier: Programming Language :: Python :: 3.10
Classifier: Programming Language :: Python :: 3.11
Classifier: License :: OSI Approved :: MIT License
Classifier: Operating System :: POSIX :: Linux
Classifier: Operating System :: MacOS :: MacOS X
Classifier: Operating System :: Microsoft :: Windows :: Windows 10
Classifier: Development Status :: 5 - Production/Stable
Requires-Python: >=3.7, <4.0
License-File: LICENSE
Requires-Dist: bleak
